patchlabel/__init__.py
patchlabel/_version.py
patchlabel/_widget.py
patchlabel/napari.yaml
patchlabel/_tests/__init__.py
patchlabel/_tests/test_widget.py
patchlabel-0.0.5.dist-info/licenses/LICENSE
patchlabel-0.0.5.dist-info/METADATA
patchlabel-0.0.5.dist-info/WHEEL
patchlabel-0.0.5.dist-info/entry_points.txt
patchlabel-0.0.5.dist-info/top_level.txt
patchlabel-0.0.5.dist-info/RECORD
