Metadata-Version: 2.4
Name: patchlabel
Version: 0.0.5
Summary: Annotate image
Author: Herearii Metuarea
Author-email: herearii.metuarea@univ-angers.fr
License: 
Project-URL: Bug Tracker, https://github.com/hereariim/patchlabel/issues
Project-URL: Documentation, https://github.com/hereariim/patchlabel#README.md
Project-URL: Source Code, https://github.com/hereariim/patchlabel
Project-URL: User Support, https://github.com/hereariim/patchlabel/issues
Classifier: Development Status :: 2 - Pre-Alpha
Classifier: Framework :: napari
Classifier: Intended Audience :: Developers
Classifier: License :: OSI Approved :: BSD License
Classifier: Operating System :: OS Independent
Classifier: Programming Language :: Python
Classifier: Programming Language :: Python :: 3
Classifier: Programming Language :: Python :: 3 :: Only
Classifier: Programming Language :: Python :: 3.10
Classifier: Programming Language :: Python :: 3.11
Classifier: Programming Language :: Python :: 3.12
Classifier: Programming Language :: Python :: 3.13
Classifier: Topic :: Scientific/Engineering :: Image Processing
Requires-Python: >=3.10
License-File: LICENSE
Requires-Dist: numpy
Requires-Dist: magicgui
Requires-Dist: qtpy
Requires-Dist: scikit-image
Requires-Dist: pillow
Provides-Extra: all
Requires-Dist: napari[all]; extra == "all"
Dynamic: license-file
